uploader/__init__.py
uploader/cleanup/__init__.py
uploader/cleanup/__main__.py
uploader/cleanup/janitor.py
uploader/metric.py
uploader/monitor.py
uploader/next.lua
uploader/requirements.txt
wf_classroom_video_uploader-1.0.11.dist-info/WHEEL
wf_classroom_video_uploader-1.0.11.dist-info/METADATA
wf_classroom_video_uploader-1.0.11.dist-info/RECORD
