Metadata-Version: 2.1
Name: wf-classroom-video-uploader
Version: 1.0.11
Summary: 
License: MIT
Author: Paul J DeCoursey
Author-email: paul@decoursey.net
Requires-Python: >=3.8,<4.0
Classifier: License :: OSI Approved :: MIT License
Classifier: Programming Language :: Python :: 3
Classifier: Programming Language :: Python :: 3.8
Classifier: Programming Language :: Python :: 3.9
Classifier: Programming Language :: Python :: 3.10
Requires-Dist: PyYAML (>=4.2b1)
Requires-Dist: click (>=7.0)
Requires-Dist: influx_line_protocol (>=0.1.5)
Requires-Dist: minio (>=4.0.17)
Requires-Dist: redis (>=3.2.1)
Requires-Dist: requests (>=2.28.1,<3.0.0)
Requires-Dist: wf-video-io (>=3.2.1)
